tfatool/_version.py
tfatool/cgi.py
tfatool/command.py
tfatool/config.py
tfatool/info.py
tfatool/sync.py
tfatool/upload.py
tfatool/util.py
tfatool-2.5.0.data/scripts/flashair-config
tfatool-2.5.0.data/scripts/flashair-util
tfatool-2.5.0.dist-info/DESCRIPTION.rst
tfatool-2.5.0.dist-info/METADATA
tfatool-2.5.0.dist-info/RECORD
tfatool-2.5.0.dist-info/WHEEL
tfatool-2.5.0.dist-info/metadata.json
tfatool-2.5.0.dist-info/top_level.txt
