Metadata-Version: 2.0
Name: tfatool
Version: 2.5.0
Summary: Tools for synchronizing files to/from and configuring the Toshiba FlashAir wireless SD card
Home-page: https://github.com/TadLeonard/tfatool
Author: Tad Leonard
Author-email: tadfleonard@gmail.com
License: MIT
Download-URL: https://github.com/TadLeonard/tfatool/archive/v2.5.0.tar.gz
Keywords: wireless sd card sdcard sync toshiba flashair
Platform: UNKNOWN
Classifier: Development Status :: 5 - Production/Stable
Classifier: Environment :: Console
Classifier: Intended Audience :: End Users/Desktop
Classifier: Intended Audience :: Developers
Classifier: Operating System :: OS Independent
Classifier: Programming Language :: Python :: 3
Classifier: Programming Language :: Python :: 3 :: Only
Classifier: Topic :: Home Automation
Classifier: Topic :: System :: Archiving
Classifier: Topic :: System :: Archiving :: Backup
Classifier: Topic :: System :: Archiving :: Mirroring
Requires-Dist: requests (>=2.9.0)
Requires-Dist: tqdm (>=3.7.1)
Requires-Dist: arrow
Requires-Dist: tabulate
